biosimulators_simularium/__init__.py
biosimulators_simularium/__main__.py
biosimulators_simularium/convert.py
biosimulators_simularium/exec.py
biosimulators_simularium/formats.py
biosimulators_simularium/geometry.py
biosimulators_simularium/io.py
biosimulators_simularium/simulation_data.py
biosimulators_simularium/tests/__init__.py
biosimulators_simularium/tests/examples/.ipynb_checkpoints/load_and_read-checkpoint.ipynb
biosimulators_simularium/tests/examples/Bar30_with_ellipse_convert.py
biosimulators_simularium/tests/examples/__init__.py
biosimulators_simularium/tests/examples/cluster_convert.py
biosimulators_simularium/tests/examples/crowding4_convert.py
biosimulators_simularium/tests/examples/load_and_read.ipynb
biosimulators_simularium/tests/examples/minE_convert.py
biosimulators_simularium/tests/examples/minE_granular_convert.py
biosimulators_simularium/tests/examples/minE_normalize_convert.py
biosimulators_simularium/tests/examples/polymer_mid_convert.py
biosimulators_simularium/tests/examples/simplified_api_convert.py
biosimulators_simularium/tests/fixtures/MinE/model.txt
biosimulators_simularium/tests/fixtures/__init__.py
biosimulators_simularium/tests/fixtures/archives/Bar30_with_ellipse/ellipse_12_12.txt
biosimulators_simularium/tests/fixtures/archives/Bar30_with_ellipse/manifest.xml
biosimulators_simularium/tests/fixtures/archives/Bar30_with_ellipse/model.txt
biosimulators_simularium/tests/fixtures/archives/Bar30_with_ellipse/tmp5y491168out.txt
biosimulators_simularium/tests/fixtures/archives/Bar30_with_ellipse/tmp5y491168out2.txt
biosimulators_simularium/tests/fixtures/archives/Chaouiya-BMC-Syst-Biol-2013-EGF-TNFa-signaling.omex
biosimulators_simularium/tests/fixtures/archives/MinE/Min1.txt
biosimulators_simularium/tests/fixtures/archives/MinE/manifest.xml
biosimulators_simularium/tests/fixtures/archives/MinE/reports.h5
biosimulators_simularium/tests/fixtures/archives/MinE.omex
biosimulators_simularium/tests/fixtures/archives/__init__.py
biosimulators_simularium-0.6.3.dist-info/LICENSE.txt
biosimulators_simularium-0.6.3.dist-info/METADATA
biosimulators_simularium-0.6.3.dist-info/WHEEL
biosimulators_simularium-0.6.3.dist-info/RECORD
