Metadata-Version: 2.1
Name: biosimulators-simularium
Version: 0.6.3
Summary: Converting Biosimulators spatial simulation outputs into a Simularium-compliant format.
Author: Alex Patrie
Author-email: alexanderpatrie@gmail.com
Requires-Python: >=3.9
Classifier: Programming Language :: Python :: 3
Classifier: Programming Language :: Python :: 3.9
Classifier: Programming Language :: Python :: 3.10
Classifier: Programming Language :: Python :: 3.11
Classifier: Programming Language :: Python :: 3.12
Requires-Dist: pyvista (>=0.44.1,<0.45.0)
Requires-Dist: simulariumio (>=1.11.0,<2.0.0)
Requires-Dist: smoldyn
Requires-Dist: toml (>=0.10.2,<0.11.0)
